{
    "/js/app.js": "/js/app.js",
    "/css/app.css": "/css/app.css",
    "/0.d31ebf45f3910dade681.hot-update.js": "/0.d31ebf45f3910dade681.hot-update.js",
    "/0.449d85ed67821fbf1a7f.hot-update.js": "/0.449d85ed67821fbf1a7f.hot-update.js",
    "/0.53b532862a73b198cda9.hot-update.js": "/0.53b532862a73b198cda9.hot-update.js",
    "/0.b962761e052e883941e9.hot-update.js": "/0.b962761e052e883941e9.hot-update.js",
    "/0.614c8f40b44f368d2ccc.hot-update.js": "/0.614c8f40b44f368d2ccc.hot-update.js",
    "/0.09841d018905461922a1.hot-update.js": "/0.09841d018905461922a1.hot-update.js",
    "/0.356823f5b844e49af5b3.hot-update.js": "/0.356823f5b844e49af5b3.hot-update.js",
    "/0.d277aa72c8400d7e9a3f.hot-update.js": "/0.d277aa72c8400d7e9a3f.hot-update.js",
    "/0.0018034a418aca8c08be.hot-update.js": "/0.0018034a418aca8c08be.hot-update.js",
    "/0.331c3a8eccdf9d92ee10.hot-update.js": "/0.331c3a8eccdf9d92ee10.hot-update.js",
    "/0.9d29be5d88b2f14228ff.hot-update.js": "/0.9d29be5d88b2f14228ff.hot-update.js",
    "/0.2a37f8061ea1b746cb3c.hot-update.js": "/0.2a37f8061ea1b746cb3c.hot-update.js",
    "/0.fb2e738ff600614e82e9.hot-update.js": "/0.fb2e738ff600614e82e9.hot-update.js",
    "/0.b8f328c8be28426d4666.hot-update.js": "/0.b8f328c8be28426d4666.hot-update.js",
    "/0.28e4a62d937e6bb6320e.hot-update.js": "/0.28e4a62d937e6bb6320e.hot-update.js",
    "/0.675440ba99a758739389.hot-update.js": "/0.675440ba99a758739389.hot-update.js",
    "/0.1075d4e6e5c3f978d130.hot-update.js": "/0.1075d4e6e5c3f978d130.hot-update.js",
    "/0.11ba92b16f4be90aff27.hot-update.js": "/0.11ba92b16f4be90aff27.hot-update.js",
    "/0.0c1192f848e0ac7705b7.hot-update.js": "/0.0c1192f848e0ac7705b7.hot-update.js",
    "/0.0506e20a860aae637511.hot-update.js": "/0.0506e20a860aae637511.hot-update.js",
    "/0.86a9b599c25b7f2019d2.hot-update.js": "/0.86a9b599c25b7f2019d2.hot-update.js",
    "/0.b63b22157612e2cceba8.hot-update.js": "/0.b63b22157612e2cceba8.hot-update.js",
    "/0.7d1c929a242b57271722.hot-update.js": "/0.7d1c929a242b57271722.hot-update.js",
    "/0.dfc112cc1ed9dc25af66.hot-update.js": "/0.dfc112cc1ed9dc25af66.hot-update.js",
    "/0.cd2e3e47f4b27a8f77bf.hot-update.js": "/0.cd2e3e47f4b27a8f77bf.hot-update.js",
    "/0.e716cf1c4b5507548f0f.hot-update.js": "/0.e716cf1c4b5507548f0f.hot-update.js",
    "/0.abaf0d831e97ccdc3fdc.hot-update.js": "/0.abaf0d831e97ccdc3fdc.hot-update.js",
    "/0.dd47e383fa6be645c503.hot-update.js": "/0.dd47e383fa6be645c503.hot-update.js",
    "/0.a632c0a9adcf7be1cc5e.hot-update.js": "/0.a632c0a9adcf7be1cc5e.hot-update.js",
    "/0.aa9699f2d71ff29e63eb.hot-update.js": "/0.aa9699f2d71ff29e63eb.hot-update.js",
    "/0.89a784eda32e19b72961.hot-update.js": "/0.89a784eda32e19b72961.hot-update.js",
    "/0.067c6731e7223f4e1a76.hot-update.js": "/0.067c6731e7223f4e1a76.hot-update.js",
    "/0.9b32a7b42f6d4f53599d.hot-update.js": "/0.9b32a7b42f6d4f53599d.hot-update.js",
    "/0.deb09b3315d5c7f9e1d0.hot-update.js": "/0.deb09b3315d5c7f9e1d0.hot-update.js",
    "/0.81d8b293ca23d28c04b7.hot-update.js": "/0.81d8b293ca23d28c04b7.hot-update.js",
    "/0.cbb5ac52560305b64697.hot-update.js": "/0.cbb5ac52560305b64697.hot-update.js",
    "/0.6645c30926067b83423d.hot-update.js": "/0.6645c30926067b83423d.hot-update.js",
    "/0.56316d942018233d416d.hot-update.js": "/0.56316d942018233d416d.hot-update.js",
    "/0.14865064829e1638dfa3.hot-update.js": "/0.14865064829e1638dfa3.hot-update.js",
    "/0.82afda2150bfbd300642.hot-update.js": "/0.82afda2150bfbd300642.hot-update.js",
    "/0.27d7d826b9ff61d0ee44.hot-update.js": "/0.27d7d826b9ff61d0ee44.hot-update.js",
    "/0.af8820c1cf1e808a3c5f.hot-update.js": "/0.af8820c1cf1e808a3c5f.hot-update.js"
}